README.rst
setup.cfg
setup.py
pybank/__init__.py
pybank/cbs.py
pybank/db.py
pybank.egg-info/PKG-INFO
pybank.egg-info/SOURCES.txt
pybank.egg-info/dependency_links.txt
pybank.egg-info/requires.txt
pybank.egg-info/top_level.txt
pybank.egg-info/zip-safe